gerstlix_python/__init__.py
gerstlix_python/metods.py
gerstlix_python-1.0.dist-info/METADATA
gerstlix_python-1.0.dist-info/WHEEL
gerstlix_python-1.0.dist-info/RECORD
