Metadata-Version: 2.1
Name: gerstlix_python
Version: 1.0
Summary: Library for simplified access to the Gerstlix API
Author: travkacode
Requires-Python: >=3.9,<4.0
Classifier: Programming Language :: Python :: 3
Classifier: Programming Language :: Python :: 3.9
Classifier: Programming Language :: Python :: 3.10
Classifier: Programming Language :: Python :: 3.11
Classifier: Programming Language :: Python :: 3.12
